LICENSE.txt
MANIFEST.in
README.rst
setup.cfg
setup.py
django_material_1.3_dj32.egg-info/PKG-INFO
django_material_1.3_dj32.egg-info/SOURCES.txt
django_material_1.3_dj32.egg-info/dependency_links.txt
django_material_1.3_dj32.egg-info/not-zip-safe
django_material_1.3_dj32.egg-info/requires.txt
django_material_1.3_dj32.egg-info/top_level.txt
material/__init__.py
material/base.py
material/compat.py
material/widgets.py
material/admin/__init__.py
material/admin/apps.py
material/conf/module_template/__init__.py-tpl
material/conf/module_template/apps.py-tpl
material/conf/module_template/models.py-tpl
material/conf/module_template/urls.py-tpl
material/conf/module_template/views.py-tpl
material/conf/module_template/migrations/__init__.py-tpl
material/conf/module_template/templates/module_name/base_module.html-tpl
material/conf/module_template/templates/module_name/menu.html-tpl
material/frontend/__init__.py
material/frontend/admin.py
material/frontend/apps.py
material/frontend/context_processors.py
material/frontend/forms.py
material/frontend/middleware.py
material/frontend/models.py
material/frontend/registry.py
material/frontend/urlconf.py
material/frontend/urls.py
material/frontend/utils.py
material/frontend/management/__init__.py
material/frontend/management/commands/__init__.py
material/frontend/management/commands/startmodule.py
material/frontend/migrations/0001_initial.py
material/frontend/migrations/0002_i18n.py
material/frontend/migrations/__init__.py
material/frontend/templates/400.html
material/frontend/templates/403.html
material/frontend/templates/404.html
material/frontend/templates/500.html
material/frontend/templates/material/frontend/base.html
material/frontend/templates/material/frontend/base_lockscreen.html
material/frontend/templates/material/frontend/base_module.html
material/frontend/templates/material/frontend/base_site.html
material/frontend/templates/material/frontend/includes/material_css.html
material/frontend/templates/material/frontend/includes/material_js.html
material/frontend/templates/material/frontend/views/confirm_delete.html
material/frontend/templates/material/frontend/views/detail.html
material/frontend/templates/material/frontend/views/form.html
material/frontend/templates/material/frontend/views/list.html
