Metadata-Version: 2.1
Name: django-material-1.3-dj32
Version: 1.3.2
Summary: Material design for django forms and admin
Home-page: http://github.com/viewflow/django-material
Author: Mikhail Podgurskiy
Author-email: kmmbvnr@gmail.com
License: BSD
Keywords: django
Platform: any
Classifier: Framework :: Django
Classifier: Framework :: Django :: 1.11
Classifier: Framework :: Django :: 2.0
Classifier: Framework :: Django :: 2.1
Classifier: Development Status :: 5 - Production/Stable
Classifier: Environment :: Web Environment
Classifier: Intended Audience :: Developers
Classifier: Intended Audience :: System Administrators
Classifier: License :: OSI Approved :: BSD License
Classifier: Operating System :: OS Independent
Classifier: Programming Language :: Python
Classifier: Programming Language :: Python :: 2.7
Classifier: Programming Language :: Python :: 3.6
Classifier: Programming Language :: Python :: 3.7
Classifier: Topic :: Software Development
Classifier: Topic :: Software Development :: User Interfaces
License-File: LICENSE.txt
